__init__.py
sounderpy/__init__.py
sounderpy/acars_data.py
sounderpy/bufkit_data.py
sounderpy/calc.py
sounderpy/model_data.py
sounderpy/obs_data.py
sounderpy/plot.py
sounderpy/sounderpy.py
sounderpy/timeseries.py
sounderpy/utils.py
sounderpy/SHARPPYMAIN/__init__.py
sounderpy/SHARPPYMAIN/ci/check_artifact_dir.py
sounderpy/SHARPPYMAIN/ci/screen.py
sounderpy/SHARPPYMAIN/datasources/__init__.py
sounderpy/SHARPPYMAIN/datasources/available.py
sounderpy/SHARPPYMAIN/datasources/data_source.py
sounderpy/SHARPPYMAIN/sharppy/io/__init__.py
sounderpy/SHARPPYMAIN/sharppy/plot/__init__.py
sounderpy/SHARPPYMAIN/sharppy/plot/skew.py
sounderpy/SHARPPYMAIN/sharppy/sharptab/__init__.py
sounderpy/SHARPPYMAIN/sharppy/sharptab/_sharppy_version.py
sounderpy/SHARPPYMAIN/sharppy/sharptab/_version.py
sounderpy/SHARPPYMAIN/sharppy/sharptab/constants.py
sounderpy/SHARPPYMAIN/sharppy/sharptab/csv.py
sounderpy/SHARPPYMAIN/sharppy/sharptab/decoder.py
sounderpy/SHARPPYMAIN/sharppy/sharptab/fire.py
sounderpy/SHARPPYMAIN/sharppy/sharptab/gui.py
sounderpy/SHARPPYMAIN/sharppy/sharptab/interp.py
sounderpy/SHARPPYMAIN/sharppy/sharptab/params.py
sounderpy/SHARPPYMAIN/sharppy/sharptab/prof_collection.py
sounderpy/SHARPPYMAIN/sharppy/sharptab/profile.py
sounderpy/SHARPPYMAIN/sharppy/sharptab/pwv.py
sounderpy/SHARPPYMAIN/sharppy/sharptab/qc_tools.py
sounderpy/SHARPPYMAIN/sharppy/sharptab/sars.py
sounderpy/SHARPPYMAIN/sharppy/sharptab/sars_cal.py
sounderpy/SHARPPYMAIN/sharppy/sharptab/sounding.py
sounderpy/SHARPPYMAIN/sharppy/sharptab/thermo.py
sounderpy/SHARPPYMAIN/sharppy/sharptab/utils.py
sounderpy/SHARPPYMAIN/sharppy/sharptab/watch_type.py
sounderpy/SHARPPYMAIN/sharppy/sharptab/winds.py
sounderpy/SHARPPYMAIN/sharppy/tests/test_binary.py
sounderpy/SHARPPYMAIN/sharppy/tests/test_decoders.py
sounderpy/SHARPPYMAIN/sharppy/tests/test_gui.py
sounderpy/SHARPPYMAIN/sharppy/tests/test_interp.py
sounderpy/SHARPPYMAIN/sharppy/tests/test_misc.py
sounderpy/SHARPPYMAIN/sharppy/tests/test_params.py
sounderpy-3.0.5.dist-info/LICENSE
sounderpy-3.0.5.dist-info/METADATA
sounderpy-3.0.5.dist-info/WHEEL
sounderpy-3.0.5.dist-info/top_level.txt
sounderpy-3.0.5.dist-info/RECORD
