Metadata-Version: 2.1
Name: sounderpy
Version: 3.0.5
Summary: Vertical Profile Data Retrieval and Analysis Tool For Python
Author-email: "Kyle J Gillett, University of North Dakota" <kyle.gillett@und.edu>
Project-URL: Docs, https://kylejgillett.github.io/sounderpy/
Project-URL: Code, https://github.com/kylejgillett/sounderpy
Project-URL: Operational Site, https://sounderpysoundings.anvil.app/
Project-URL: PyPi, https://pypi.org/project/sounderpy/
Project-URL: My Website, https://kylegillettphoto.com
Keywords: meteorology,science,data-analysis,weather,forecasting
Classifier: Programming Language :: Python
Classifier: Programming Language :: Python :: 3.10
Classifier: Programming Language :: Python :: 3.11
Classifier: Topic :: Scientific/Engineering
Classifier: Topic :: Scientific/Engineering :: Atmospheric Science
Classifier: Intended Audience :: Science/Research
Classifier: Operating System :: OS Independent
Classifier: License :: OSI Approved :: MIT License
Requires-Python: >=3.1
License-File: LICENSE
Requires-Dist: cartopy >=0.21.0
Requires-Dist: cdsapi >=0.7.3
Requires-Dist: ecape-parcel >=1.2.0.2
Requires-Dist: matplotlib >=3.3.0
Requires-Dist: metpy >=1.5.1
Requires-Dist: netcdf4 >=1.6.4
Requires-Dist: numpy >=1.20.0
Requires-Dist: pandas >=1.2.0
Requires-Dist: siphon >=0.9
Requires-Dist: scipy >=1.10.1
Requires-Dist: xarray >=0.18.0
